cryptonewsmcp/__init__.py
cryptonewsmcp/py.typed
cryptonewsmcp/server.py
cryptonewsmcp/utils.py
cryptonewsmcp/types/__init__.py
cryptonewsmcp/types/news.py
cryptonewsmcp-0.2.0.dist-info/METADATA
cryptonewsmcp-0.2.0.dist-info/WHEEL
cryptonewsmcp-0.2.0.dist-info/entry_points.txt
cryptonewsmcp-0.2.0.dist-info/licenses/LICENSE
cryptonewsmcp-0.2.0.dist-info/RECORD
