Metadata-Version: 2.4
Name: cryptonewsmcp
Version: 0.2.0
Author-email: narumi <toucans-cutouts0f@icloud.com>
License-File: LICENSE
Requires-Python: >=3.12
Requires-Dist: beautifulsoup4>=4.13.3
Requires-Dist: feedparser>=6.0.11
Requires-Dist: loguru>=0.7.3
Requires-Dist: markdownify>=1.1.0
Requires-Dist: mcp[cli]>=1.6.0
Requires-Dist: python-dateutil>=2.9.0.post0
